{
  "posodobljenoOb": "2026-07-10T11:08:08.692Z",
  "indeksi": [
    {
      "simbol": "^GSPC",
      "ime": "S&P 500",
      "vrednost": 7543.64,
      "sprememba_pct": 0.81
    },
    {
      "simbol": "^NDX",
      "ime": "Nasdaq 100",
      "vrednost": 29727.098,
      "sprememba_pct": 1.62
    },
    {
      "simbol": "^GDAXI",
      "ime": "DAX",
      "vrednost": 25136.32,
      "sprememba_pct": 0.07
    },
    {
      "simbol": "^N225",
      "ime": "Nikkei 225",
      "vrednost": 68557.73,
      "sprememba_pct": 1.2
    }
  ],
  "surovine": [
    {
      "simbol": "GC=F",
      "ime": "Zlato",
      "vrednost": 4115.1,
      "sprememba_pct": -0.62,
      "enota": "USD/oz"
    },
    {
      "simbol": "CL=F",
      "ime": "WTI nafta",
      "vrednost": 72.22,
      "sprememba_pct": 0.19,
      "enota": "USD/sod"
    },
    {
      "simbol": "BZ=F",
      "ime": "Brent nafta",
      "vrednost": 76.47,
      "sprememba_pct": 0.22,
      "enota": "USD/sod"
    }
  ],
  "forex": [
    {
      "simbol": "EURUSD=X",
      "ime": "EUR/USD",
      "vrednost": 1.1436,
      "sprememba_pct": 0.02
    }
  ],
  "obveznice": [
    {
      "simbol": "^TNX",
      "ime": "10Y US Treasury",
      "vrednost": 4.539,
      "sprememba_pct": -0.66,
      "enota": "%"
    }
  ],
  "kripto": [
    {
      "simbol": "BTC-USD",
      "ime": "Bitcoin",
      "vrednost": 64385.68,
      "sprememba_pct": 1.9,
      "enota": "USD"
    }
  ],
  "vix": {
    "simbol": "^VIX",
    "ime": "VIX",
    "vrednost": 15.9,
    "sprememba_pct": 0.38
  }
}